cloudianapi/__init__.py
cloudianapi/client.py
cloudianapi/components/__init__.py
cloudianapi/components/billing.py
cloudianapi/components/bppolicy.py
cloudianapi/components/group.py
cloudianapi/components/monitor.py
cloudianapi/components/qos.py
cloudianapi/components/ratingplan.py
cloudianapi/components/system.py
cloudianapi/components/tiering.py
cloudianapi/components/usage.py
cloudianapi/components/user.py
cloudianapi/components/whitelist.py
cloudianapi/core/__init__.py
cloudianapi/core/basecomponent.py
cloudianapi/core/requestors.py
cloudianapi/tools/__init__.py
cloudianapi/tools/statistics.py
cloudianapi-0.2.4.dist-info/METADATA
cloudianapi-0.2.4.dist-info/RECORD
cloudianapi-0.2.4.dist-info/WHEEL
cloudianapi-0.2.4.dist-info/top_level.txt
