Metadata-Version: 2.1
Name: cloudianapi
Version: 0.2.4
Summary: Non-official Cloudian (TM) REST Admin API Client
Home-page: https://github.com/romerojunior/cloudian-api
Author: Romero Galiza Jr
Author-email: rgaliza@schubergphilis.com
License: Apache License Version 2.0
Download-URL: https://github.com/romerojunior/cloudian-api/archive/0.2.4.tar.gz
Keywords: cloudian,api-client
Platform: Any
